developmentEmailDashboard
